examples/__init__.py
examples/titanic/__init__.py
examples/titanic/pyfuzz_titanic.py
examples/titanic/titanic.py
pyfuzz/__init__.py
pyfuzz/byte_mutations.py
pyfuzz/coverage.py
pyfuzz/fuzz_data_interpreter.py
pyfuzz/fuzzers.py
pyfuzz/runners.py
pyfuzz/string_mutations.py
pyfuzz/test_programs.py
pyfuzz_tool-0.0.5.dist-info/LICENSE
pyfuzz_tool-0.0.5.dist-info/METADATA
pyfuzz_tool-0.0.5.dist-info/WHEEL
pyfuzz_tool-0.0.5.dist-info/top_level.txt
pyfuzz_tool-0.0.5.dist-info/RECORD
